LocationSimulate/__init__.py
LocationSimulate/simulate.py
robotframework_locationsimulation-0.1.3.dist-info/METADATA
robotframework_locationsimulation-0.1.3.dist-info/WHEEL
robotframework_locationsimulation-0.1.3.dist-info/top_level.txt
robotframework_locationsimulation-0.1.3.dist-info/RECORD
