Metadata-Version: 2.4
Name: robotframework-LocationSimulation
Version: 0.1.3
Summary: A Robot Framework function to simulate the Geo Location for location based testing.
Author-email: Jagadeesh Vedula <vedulajagadeesh1994@gmail.com>
Project-URL: Homepage, https://github.com/JagadeeshVedula/LocationSimulator
Project-URL: Bug Tracker, https://github.com/JagadeeshVedula/LocationSimulator/issues
Classifier: Programming Language :: Python :: 3
Classifier: License :: OSI Approved :: MIT License
Classifier: Operating System :: OS Independent
Classifier: Framework :: Robot Framework
Classifier: Topic :: Software Development :: Testing
Requires-Python: >=3.8
Requires-Dist: robotframework>=5.0
Requires-Dist: robotframework-appiumlibrary
Requires-Dist: geopy
